pyro_lexer.py
pyro_lexer-0.6.2.dist-info/METADATA
pyro_lexer-0.6.2.dist-info/WHEEL
pyro_lexer-0.6.2.dist-info/entry_points.txt
pyro_lexer-0.6.2.dist-info/top_level.txt
pyro_lexer-0.6.2.dist-info/RECORD
